MANIFEST.in
README.md
setup.py
bysy/DB.py
bysy/TIME.py
bysy/__init__.py
bysy/__main__.py
bysy/alias.py
bysy/config.json
bysy/configure.py
bysy/deleteentry.py
bysy/echotime.py
bysy/initialize.py
bysy/loglist.py
bysy/resume.py
bysy/start.py
bysy/stop.py
bysy/template.json
bysy.egg-info/PKG-INFO
bysy.egg-info/SOURCES.txt
bysy.egg-info/dependency_links.txt
bysy.egg-info/entry_points.txt
bysy.egg-info/not-zip-safe
bysy.egg-info/top_level.txt