Metadata-Version: 1.1
Name: bysy
Version: 0.9.2
Summary: Self-management time logging tool
Home-page: https://github.com/Godje/bysy
Author: Daniel Mayovskiy
Author-email: daniel.mayovskiy@gmail.com
License: MPL 2.0
Keywords: time,logging,management
Platform: UNKNOWN
Classifier: Development Status :: 4 - Beta
Classifier: Intended Audience :: Developers
